sna_prediction/__init__.py
sna_prediction/graph_plot.py
sna_prediction/main.py
sna_prediction/slider.py
sna_prediction/tweet_extract.py
sna_prediction-1.1.dist-info/LICENSE
sna_prediction-1.1.dist-info/METADATA
sna_prediction-1.1.dist-info/WHEEL
sna_prediction-1.1.dist-info/entry_points.txt
sna_prediction-1.1.dist-info/top_level.txt
sna_prediction-1.1.dist-info/RECORD
