Metadata-Version: 2.1
Name: sna-prediction
Version: 1.1
Summary: A python package to predict outcome of an event based on type of data it is fed to.For now it is Loksabha 2019 Elections
Home-page: https://github.com/itsDevhere/social-network-analysis
Author: Devpratim Das , Rana Mondal , Souvik Das , Soumyajeet Bose
Author-email: 
License: MIT
Platform: UNKNOWN
Classifier: License :: OSI Approved :: MIT License
Classifier: Programming Language :: Python :: 3
Requires-Dist: tweepy
Requires-Dist: textblob
Requires-Dist: wordcloud
Requires-Dist: PyQt5
Requires-Dist: pandas
Requires-Dist: numpy
Requires-Dist: networkx (==2.3)
Requires-Dist: matplotlib
Requires-Dist: emoji
